[{"name":"sql.active_record","payload":{"sql":"BEGIN","name":null,"connection_id":70324354190580,"statement_name":null,"binds":[]},"time":"2015-06-01T13:59:23.073+08:00","transaction_id":"2e117e140ec97a0bf973","end":"2015-06-01T13:59:23.074+08:00","children":[],"duration":0.696},{"name":"sql.active_record","payload":{"sql":"SELECT  1 AS one FROM \"users\"  WHERE \"users\".\"email\" = 'hiphubryan@gmail.com' LIMIT 1","name":"User Exists","connection_id":70324354190580,"statement_name":null,"binds":[]},"time":"2015-06-01T13:59:23.083+08:00","transaction_id":"2e117e140ec97a0bf973","end":"2015-06-01T13:59:23.085+08:00","children":[],"duration":1.564},{"name":"sql.active_record","payload":{"sql":"INSERT INTO \"users\" (\"created_at\", \"email\", \"encrypted_password\", \"updated_at\") VALUES ($1, $2, $3, $4) RETURNING \"id\"","name":"SQL","connection_id":70324354190580,"statement_name":"a3","binds":[[{"oid_type":{},"array":false,"name":"created_at","sql_type":"timestamp without time zone","null":true,"limit":null,"precision":null,"scale":null,"type":"datetime","default":null,"default_function":null,"primary":false,"coder":null},"2015-06-01 05:59:23.087460"],[{"oid_type":{},"array":false,"name":"email","sql_type":"character varying(255)","null":false,"limit":255,"precision":null,"scale":null,"type":"string","default":"","default_function":null,"primary":false,"coder":null},"hiphubryan@gmail.com"],[{"oid_type":{},"array":false,"name":"encrypted_password","sql_type":"character varying(255)","null":false,"limit":255,"precision":null,"scale":null,"type":"string","default":"","default_function":null,"primary":false,"coder":null},"$2a$10$QypJTIh0msUWKNG9PH2Qr.1WXoEdfM23XyXhJDDPWvX8zbXofNM5W"],[{"oid_type":{},"array":false,"name":"updated_at","sql_type":"timestamp without time zone","null":true,"limit":null,"precision":null,"scale":null,"type":"datetime","default":null,"default_function":null,"primary":false,"coder":null},"2015-06-01 05:59:23.087460"]]},"time":"2015-06-01T13:59:23.088+08:00","transaction_id":"2e117e140ec97a0bf973","end":"2015-06-01T13:59:23.106+08:00","children":[],"duration":17.308},{"name":"sql.active_record","payload":{"sql":"COMMIT","name":null,"connection_id":70324354190580,"statement_name":null,"binds":[]},"time":"2015-06-01T13:59:23.111+08:00","transaction_id":"2e117e140ec97a0bf973","end":"2015-06-01T13:59:23.112+08:00","children":[],"duration":1.0759999999999998},{"name":"sql.active_record","payload":{"sql":"BEGIN","name":null,"connection_id":70324354190580,"statement_name":null,"binds":[]},"time":"2015-06-01T13:59:23.116+08:00","transaction_id":"2e117e140ec97a0bf973","end":"2015-06-01T13:59:23.117+08:00","children":[],"duration":1.3010000000000002},{"name":"sql.active_record","payload":{"sql":"UPDATE \"users\" SET \"current_sign_in_at\" = $1, \"current_sign_in_ip\" = $2, \"last_sign_in_at\" = $3, \"last_sign_in_ip\" = $4, \"sign_in_count\" = $5, \"updated_at\" = $6 WHERE \"users\".\"id\" = 1","name":"SQL","connection_id":70324354190580,"statement_name":"a4","binds":[[{"oid_type":{},"array":false,"name":"current_sign_in_at","sql_type":"timestamp without time zone","null":true,"limit":null,"precision":null,"scale":null,"type":"datetime","default":null,"default_function":null,"primary":false,"coder":null},"2015-06-01 05:59:23.114991"],[{"oid_type":{},"array":false,"name":"current_sign_in_ip","sql_type":"character varying(255)","null":true,"limit":255,"precision":null,"scale":null,"type":"string","default":null,"default_function":null,"primary":false,"coder":null},"127.0.0.1"],[{"oid_type":{},"array":false,"name":"last_sign_in_at","sql_type":"timestamp without time zone","null":true,"limit":null,"precision":null,"scale":null,"type":"datetime","default":null,"default_function":null,"primary":false,"coder":null},"2015-06-01 05:59:23.114991"],[{"oid_type":{},"array":false,"name":"last_sign_in_ip","sql_type":"character varying(255)","null":true,"limit":255,"precision":null,"scale":null,"type":"string","default":null,"default_function":null,"primary":false,"coder":null},"127.0.0.1"],[{"oid_type":{},"array":false,"name":"sign_in_count","sql_type":"integer","null":false,"limit":null,"precision":null,"scale":null,"type":"integer","default":0,"default_function":null,"primary":false,"coder":null},1],[{"oid_type":{},"array":false,"name":"updated_at","sql_type":"timestamp without time zone","null":true,"limit":null,"precision":null,"scale":null,"type":"datetime","default":null,"default_function":null,"primary":false,"coder":null},"2015-06-01 05:59:23.119248"]]},"time":"2015-06-01T13:59:23.121+08:00","transaction_id":"2e117e140ec97a0bf973","end":"2015-06-01T13:59:23.121+08:00","children":[],"duration":0.878},{"name":"sql.active_record","payload":{"sql":"COMMIT","name":null,"connection_id":70324354190580,"statement_name":null,"binds":[]},"time":"2015-06-01T13:59:23.124+08:00","transaction_id":"2e117e140ec97a0bf973","end":"2015-06-01T13:59:23.125+08:00","children":[],"duration":0.687},{"name":"process_action.action_controller","payload":{"controller":"Devise::RegistrationsController","action":"create","params":{"utf8":"✓","authenticity_token":"7es1v8rRvYKgz4P72tI4ljSKjZmuGcz//MaeCN0/3Lo=","user":{"email":"hiphubryan@gmail.com","password":"[FILTERED]","password_confirmation":"[FILTERED]"},"commit":"Sign up","action":"create","controller":"devise/registrations"},"format":"html","method":"POST","path":"/users","status":302,"view_runtime":null,"db_runtime":20.117999999999995},"time":"2015-06-01T13:59:22.970+08:00","transaction_id":"5be7934f63fe9cbc4830","end":"2015-06-01T13:59:23.146+08:00","children":[],"duration":176.417}]